blueflow/README.py
blueflow/__init__.py
blueflow/__main__.py
blueflow/config.env
blueflow/env.py
blueflow/host.py
blueflow/logger.py
blueflow/notebooks.py
blueflow/sample.env
blueflow/urls.py
blueflow/.abcli/actions.sh
blueflow/.abcli/aka.sh
blueflow/.abcli/alias.sh
blueflow/.abcli/aws_batch.sh
blueflow/.abcli/docker.sh
blueflow/.abcli/huggingface.sh
blueflow/.abcli/jupyter-notebook.sh
blueflow/.abcli/meta_scripts.sh
blueflow/.abcli/notebooks-and-scripts.sh
blueflow/.abcli/sagemaker.sh
blueflow/.abcli/scripts.sh
blueflow/.abcli/workflow.sh
blueflow/.abcli/aws_batch/browse.sh
blueflow/.abcli/aws_batch/cat.sh
blueflow/.abcli/aws_batch/eval.sh
blueflow/.abcli/aws_batch/list.sh
blueflow/.abcli/aws_batch/submit.sh
blueflow/.abcli/docker/browse.sh
blueflow/.abcli/docker/build.sh
blueflow/.abcli/docker/clear.sh
blueflow/.abcli/docker/push.sh
blueflow/.abcli/docker/run.sh
blueflow/.abcli/docker/seed.sh
blueflow/.abcli/jupyter-notebook/build.sh
blueflow/.abcli/jupyter-notebook/code.sh
blueflow/.abcli/jupyter-notebook/connect.sh
blueflow/.abcli/jupyter-notebook/create.sh
blueflow/.abcli/jupyter-notebook/host.sh
blueflow/.abcli/jupyter-notebook/open.sh
blueflow/.abcli/tests/README.sh
blueflow/.abcli/tests/help.sh
blueflow/.abcli/tests/version.sh
blueflow/.abcli/tests/workflow_runner.sh
blueflow/.abcli/workflow/config.sh
blueflow/.abcli/workflow/create.sh
blueflow/.abcli/workflow/monitor.sh
blueflow/.abcli/workflow/submit.sh
blueflow/assets/__init__.py
blueflow/assets/template.ipynb
blueflow/aws_batch/__init__.py
blueflow/aws_batch/__main__.py
blueflow/aws_batch/submission.py
blueflow/help/__init__.py
blueflow/help/__main__.py
blueflow/help/functions.py
blueflow/help/huggingface.py
blueflow/help/workflow.py
blueflow/sagemaker/__init__.py
blueflow/workflow/README.py
blueflow/workflow/__init__.py
blueflow/workflow/__main__.py
blueflow/workflow/dot_file.py
blueflow/workflow/generic.py
blueflow/workflow/patterns/__init__.py
blueflow/workflow/patterns/__main__.py
blueflow-4.857.1.dist-info/LICENSE
blueflow-4.857.1.dist-info/METADATA
blueflow-4.857.1.dist-info/WHEEL
blueflow-4.857.1.dist-info/top_level.txt
blueflow-4.857.1.dist-info/RECORD
