Metadata-Version: 2.2
Name: blueflow
Version: 4.857.1
Summary: 📜 workflow management on aws batch and more.
Home-page: https://github.com/kamangir/notebooks-and-scripts
Author: Arash Abadpour (Kamangir)
Author-email: arash@kamangir.net
License: Public Domain
Classifier: Programming Language :: Python :: 3
Classifier: Programming Language :: Unix Shell
Classifier: License :: Public Domain
Classifier: Operating System :: OS Independent
License-File: LICENSE
Requires-Dist: blueness
Requires-Dist: abcli
Requires-Dist: beautifulsoup4
Requires-Dist: blue_objects
Requires-Dist: boto3
Requires-Dist: geojson
Requires-Dist: geopandas
Requires-Dist: ipdb
Requires-Dist: matplotlib
Requires-Dist: networkx
Requires-Dist: opencv-python
Requires-Dist: pydot
Requires-Dist: pylint
Requires-Dist: pymysql
Requires-Dist: pytest
Requires-Dist: python-dotenv[cli]
Requires-Dist: pyyaml
Requires-Dist: requests
Requires-Dist: tqdm
Dynamic: author
Dynamic: author-email
Dynamic: classifier
Dynamic: description
Dynamic: description-content-type
Dynamic: home-page
Dynamic: license
Dynamic: requires-dist
Dynamic: summary
